pygments_lammps/__init__.py
pygments_lammps/lammps.py
pygments_lammps-1.1.1.dist-info/LICENSE
pygments_lammps-1.1.1.dist-info/METADATA
pygments_lammps-1.1.1.dist-info/WHEEL
pygments_lammps-1.1.1.dist-info/entry_points.txt
pygments_lammps-1.1.1.dist-info/top_level.txt
pygments_lammps-1.1.1.dist-info/RECORD
