Metadata-Version: 2.1
Name: pygments-lammps
Version: 1.1.1
Summary: A Pygments lexer for LAMMPS input scripts
Author-email: Richard Berger <richard.berger@outlook.com>, Axel Kohlmeyer <akohlmey@gmail.com>
License: GPL-2.0-only
Project-URL: Homepage, https://github.com/lammps/pygments-lammps
Keywords: lexer,LAMMPS
Classifier: License :: OSI Approved :: GNU General Public License v2 (GPLv2)
Classifier: Programming Language :: Python
Classifier: Programming Language :: Python :: 3
Requires-Python: >=3.5
License-File: LICENSE
Requires-Dist: pygments
